pyresolver/__init__.py
pyresolver/cli.py
pyresolver/ai/__init__.py
pyresolver/ai/predictor.py
pyresolver/ai/trainer.py
pyresolver/core/__init__.py
pyresolver/core/exceptions.py
pyresolver/core/models.py
pyresolver/core/performance.py
pyresolver/core/resolver.py
pyresolver/data/__init__.py
pyresolver/data/pypi_client.py
pyresolver/integration/__init__.py
ai_pyresolver-0.1.0.dist-info/METADATA
ai_pyresolver-0.1.0.dist-info/WHEEL
ai_pyresolver-0.1.0.dist-info/entry_points.txt
ai_pyresolver-0.1.0.dist-info/licenses/LICENSE
ai_pyresolver-0.1.0.dist-info/RECORD
