Metadata-Version: 2.4
Name: ai-pyresolver
Version: 0.1.0
Summary: AI-powered Python dependency resolver
Project-URL: Homepage, https://github.com/pyresolver/pyresolver
Project-URL: Documentation, https://pyresolver.readthedocs.io
Project-URL: Repository, https://github.com/pyresolver/pyresolver
Project-URL: Issues, https://github.com/pyresolver/pyresolver/issues
Author-email: PyResolver Team <team@pyresolver.dev>
License-Expression: MIT
License-File: LICENSE
Keywords: ai,dependency,ml,packaging,python,resolver
Classifier: Development Status :: 3 - Alpha
Classifier: Intended Audience :: Developers
Classifier: License :: OSI Approved :: MIT License
Classifier: Programming Language :: Python :: 3
Classifier: Programming Language :: Python :: 3.9
Classifier: Programming Language :: Python :: 3.10
Classifier: Programming Language :: Python :: 3.11
Classifier: Programming Language :: Python :: 3.12
Classifier: Topic :: Software Development :: Libraries :: Python Modules
Classifier: Topic :: System :: Software Distribution
Requires-Python: >=3.9
Requires-Dist: aiohttp>=3.8.0
Requires-Dist: click>=8.0.0
Requires-Dist: networkx>=2.6.0
Requires-Dist: numpy>=1.21.0
Requires-Dist: packaging>=21.0
Requires-Dist: pandas>=1.3.0
Requires-Dist: pydantic>=2.0.0
Requires-Dist: requests>=2.25.0
Requires-Dist: rich>=12.0.0
Requires-Dist: scikit-learn>=1.0.0
Requires-Dist: sqlalchemy>=2.0.0
Requires-Dist: torch>=2.0.0
Provides-Extra: api
Requires-Dist: fastapi>=0.100.0; extra == 'api'
Requires-Dist: redis>=4.5.0; extra == 'api'
Requires-Dist: uvicorn>=0.20.0; extra == 'api'
Provides-Extra: dev
Requires-Dist: black>=23.0.0; extra == 'dev'
Requires-Dist: isort>=5.12.0; extra == 'dev'
Requires-Dist: mypy>=1.0.0; extra == 'dev'
Requires-Dist: pre-commit>=3.0.0; extra == 'dev'
Requires-Dist: pytest-asyncio>=0.21.0; extra == 'dev'
Requires-Dist: pytest-cov>=4.0.0; extra == 'dev'
Requires-Dist: pytest>=7.0.0; extra == 'dev'
Provides-Extra: docs
Requires-Dist: mkdocs-material>=9.0.0; extra == 'docs'
Requires-Dist: mkdocs>=1.4.0; extra == 'docs'
Requires-Dist: mkdocstrings[python]>=0.20.0; extra == 'docs'
